tap_randomdata/__init__.py
tap_randomdata/schemas/address.json
tap_randomdata/schemas/company.json
tap_randomdata/schemas/food.json
tap_randomdata/schemas/restaurant.json
tap_randomdata/schemas/vehicle.json
tap_randomdata-0.2.0.dist-info/entry_points.txt
tap_randomdata-0.2.0.dist-info/WHEEL
tap_randomdata-0.2.0.dist-info/METADATA
tap_randomdata-0.2.0.dist-info/RECORD
